setup.py
jujube_pill999.egg-info/PKG-INFO
jujube_pill999.egg-info/SOURCES.txt
jujube_pill999.egg-info/dependency_links.txt
jujube_pill999.egg-info/entry_points.txt
jujube_pill999.egg-info/top_level.txt
pypi_test/__init__.py