Metadata-Version: 1.0
Name: jujube-pill999
Version: 0.0.1
Summary: 吃枣药丸
Home-page: https://zhuanlan.zhihu.com/p/26159930
Author: xlzd
Author-email: wwwwu@gmail.com
License: UNKNOWN
Platform: UNKNOWN
